LICENSE
llama_agi/__init__.py
llama_agi/default_task_prompts.py
llama_agi/execution_agent/SimpleExecutionAgent.py
llama_agi/execution_agent/ToolExecutionAgent.py
llama_agi/execution_agent/__init__.py
llama_agi/execution_agent/base.py
llama_agi/runners/AutoAGIRunner.py
llama_agi/runners/AutoStreamlitAGIRunner.py
llama_agi/runners/__init__.py
llama_agi/runners/base.py
llama_agi/task_manager/LlamaTaskManager.py
llama_agi/task_manager/__init__.py
llama_agi/task_manager/base.py
llama_agi/tools/NoteTakingTools.py
llama_agi/tools/WebpageSearchTool.py
llama_agi/tools/__init__.py
llama_agi/utils.py
llama_agi-0.2.0.dist-info/LICENSE
llama_agi-0.2.0.dist-info/METADATA
llama_agi-0.2.0.dist-info/WHEEL
llama_agi-0.2.0.dist-info/RECORD
