Metadata-Version: 2.1
Name: llama-agi
Version: 0.2.0
Summary: Building AGI loops using LlamaIndex and Langchain
Home-page: https://github.com/run-llama/llama-lab/tree/main/llama_agi
License: MIT
Keywords: LLM,LlamaIndex,Langchain,AGI
Requires-Python: >=3.8.1,<4.0
Classifier: License :: OSI Approved :: MIT License
Classifier: Programming Language :: Python :: 3
Classifier: Programming Language :: Python :: 3.9
Classifier: Programming Language :: Python :: 3.10
Classifier: Programming Language :: Python :: 3.11
Requires-Dist: altair (==4.2.2)
Requires-Dist: google-api-python-client (>=2.87.0)
Requires-Dist: langchain (==0.0.154)
Requires-Dist: llama-index (==0.6.13)
Requires-Dist: streamlit (==1.21.0)
Requires-Dist: transformers (>=0.4.29)
Project-URL: Repository, https://github.com/run-llama/llama-lab/tree/main/llama_agi
